neon_audio/__init__.py
neon_audio/__main__.py
neon_audio/cli.py
neon_audio/service.py
neon_audio/utils.py
neon_audio/tts/__init__.py
neon_audio/tts/neon.py
tests/__init__.py
tests/api_method_tests.py
tests/unit_tests.py
tests/test_objects/__init__.py
neon_audio-1.7.0.dist-info/LICENSE.md
neon_audio-1.7.0.dist-info/METADATA
neon_audio-1.7.0.dist-info/WHEEL
neon_audio-1.7.0.dist-info/entry_points.txt
neon_audio-1.7.0.dist-info/top_level.txt
neon_audio-1.7.0.dist-info/zip-safe
neon_audio-1.7.0.dist-info/RECORD
