Metadata-Version: 2.1
Name: neon-audio
Version: 1.7.0
Summary: Neon Audio Module
Home-page: https://github.com/NeonGeckoCom/neon_audio
Author: Neongecko
Author-email: developers@neon.ai
License: BSD-3-Clause
Classifier: Intended Audience :: Developers
Classifier: Programming Language :: Python :: 3
License-File: LICENSE.md
Requires-Dist: ovos-audio~=0.3
Requires-Dist: ovos-utils>=0.0.35,~=0.0
Requires-Dist: ovos-config~=0.1
Requires-Dist: phoneme-guesser~=0.1
Requires-Dist: ovos-plugin-manager~=0.1
Requires-Dist: neon-utils[network,sentry,signal]~=1.13
Requires-Dist: click~=8.0
Requires-Dist: click-default-group~=1.2
Requires-Dist: ovos-bus-client>=0.0.3,~=0.0
Requires-Dist: ovos-audio-plugin-simple~=0.1
Requires-Dist: ovos-plugin-common-play>=0.0.6,~=0.0
Requires-Dist: ovos-ocp-m3u-plugin>=0.0.1,~=0.0
Requires-Dist: ovos-ocp-rss-plugin>=0.0.2,~=0.0
Requires-Dist: ovos-ocp-files-plugin~=0.13
Requires-Dist: ovos-ocp-news-plugin>=0.0.3,~=0.0
Provides-Extra: docker
Requires-Dist: neon-lang-plugin-libretranslate>=0.2.1,~=0.2; extra == "docker"
Requires-Dist: ovos-tts-plugin-mimic~=0.2; extra == "docker"
Requires-Dist: neon-tts-plugin-coqui>=0.8.1,~=0.7; extra == "docker"
